{
  "input": "outputs/closure_stop_after_final_smoke.json",
  "baseline": "baseline",
  "bootstrap_iterations": 1000,
  "metrics": [
    {
      "metric": "first_final_correct",
      "baseline": "baseline",
      "conditions": [
        {
          "condition": "baseline",
          "n": 2,
          "successes": 0,
          "accuracy": 0.0,
          "wilson95": {
            "center": 0.32880988624667346,
            "low": 0.0,
            "high": 0.6576197724933469
          },
          "paired_diff_vs_baseline": {
            "mean_diff": 0.0,
            "low": 0.0,
            "high": 0.0
          },
          "mcnemar": {
            "baseline_wrong_candidate_right": 0,
            "baseline_right_candidate_wrong": 0,
            "discordant_total": 0,
            "exact_two_sided_p": 1.0
          }
        },
        {
          "condition": "layer27_t0.75",
          "n": 2,
          "successes": 0,
          "accuracy": 0.0,
          "wilson95": {
            "center": 0.32880988624667346,
            "low": 0.0,
            "high": 0.6576197724933469
          },
          "paired_diff_vs_baseline": {
            "mean_diff": 0.0,
            "low": 0.0,
            "high": 0.0
          },
          "mcnemar": {
            "baseline_wrong_candidate_right": 0,
            "baseline_right_candidate_wrong": 0,
            "discordant_total": 0,
            "exact_two_sided_p": 1.0
          }
        }
      ]
    },
    {
      "metric": "last_final_correct",
      "baseline": "baseline",
      "conditions": [
        {
          "condition": "baseline",
          "n": 2,
          "successes": 0,
          "accuracy": 0.0,
          "wilson95": {
            "center": 0.32880988624667346,
            "low": 0.0,
            "high": 0.6576197724933469
          },
          "paired_diff_vs_baseline": {
            "mean_diff": 0.0,
            "low": 0.0,
            "high": 0.0
          },
          "mcnemar": {
            "baseline_wrong_candidate_right": 0,
            "baseline_right_candidate_wrong": 0,
            "discordant_total": 0,
            "exact_two_sided_p": 1.0
          }
        },
        {
          "condition": "layer27_t0.75",
          "n": 2,
          "successes": 0,
          "accuracy": 0.0,
          "wilson95": {
            "center": 0.32880988624667346,
            "low": 0.0,
            "high": 0.6576197724933469
          },
          "paired_diff_vs_baseline": {
            "mean_diff": 0.0,
            "low": 0.0,
            "high": 0.0
          },
          "mcnemar": {
            "baseline_wrong_candidate_right": 0,
            "baseline_right_candidate_wrong": 0,
            "discordant_total": 0,
            "exact_two_sided_p": 1.0
          }
        }
      ]
    }
  ],
  "auxiliary": {
    "conditions": [
      {
        "condition": "baseline",
        "n": 2,
        "strict_stop_rate": 0.0,
        "strict_malformed_rate": 1.0,
        "mean_generated_tokens": 32.0,
        "mean_repetition_rate": 0.0
      },
      {
        "condition": "layer27_t0.75",
        "n": 2,
        "strict_stop_rate": 0.5,
        "strict_malformed_rate": 0.5,
        "mean_generated_tokens": 24.5,
        "mean_repetition_rate": 0.08333333333333333
      }
    ]
  }
}